{"nodes": [{"id": "frontend_types_proposal_version_ts", "label": "proposal-version.ts", "file_type": "code", "source_file": "frontend/types/proposal-version.ts", "source_location": "L1"}, {"id": "proposal_version_getactionlabel", "label": "getActionLabel()", "file_type": "code", "source_file": "frontend/types/proposal-version.ts", "source_location": "L15"}, {"id": "proposal_version_getactioncolor", "label": "getActionColor()", "file_type": "code", "source_file": "frontend/types/proposal-version.ts", "source_location": "L32"}], "edges": [{"source": "frontend_types_proposal_version_ts", "target": "frontend_types_proposal", "relation": "imports_from", "confidence": "EXTRACTED", "source_file": "frontend/types/proposal-version.ts", "source_location": "L1", "weight": 1.0}, {"source": "frontend_types_proposal_version_ts", "target": "proposal_version_getactionlabel", "relation": "contains", "confidence": "EXTRACTED", "source_file": "frontend/types/proposal-version.ts", "source_location": "L15", "weight": 1.0}, {"source": "frontend_types_proposal_version_ts", "target": "proposal_version_getactioncolor", "relation": "contains", "confidence": "EXTRACTED", "source_file": "frontend/types/proposal-version.ts", "source_location": "L32", "weight": 1.0}], "raw_calls": []}